googleadsquerytool.py
googleadsquerytool-0.1.8.dist-info/METADATA
googleadsquerytool-0.1.8.dist-info/WHEEL
googleadsquerytool-0.1.8.dist-info/RECORD
