Metadata-Version: 2.1
Name: googleadsquerytool
Version: 0.1.8
Summary: This is a package you can use to query reporting data from the Google Ads API.
Author: caspercrause
Author-email: ccrause07@gmail.com
Requires-Python: >=3.9,<3.14
Classifier: Programming Language :: Python :: 3
Classifier: Programming Language :: Python :: 3.9
Classifier: Programming Language :: Python :: 3.10
Classifier: Programming Language :: Python :: 3.11
Classifier: Programming Language :: Python :: 3.12
Requires-Dist: google-ads (==28.2.0)
Requires-Dist: pandas (>1.4)
